grouse/__init__.py
grouse/dtos.py
grouse/grounded_qa_evaluator.py
grouse/main.py
grouse/meta_evaluator.py
grouse/plot.py
grouse/register_models.py
grouse/utils.py
grouse/gpt4_prompts/answer_relevancy.txt.jinja
grouse/gpt4_prompts/completeness.txt.jinja
grouse/gpt4_prompts/faithfulness.txt.jinja
grouse/gpt4_prompts/usefulness.txt.jinja
grouse-0.4.2.dist-info/LICENSE.txt
grouse-0.4.2.dist-info/METADATA
grouse-0.4.2.dist-info/WHEEL
grouse-0.4.2.dist-info/entry_points.txt
grouse-0.4.2.dist-info/top_level.txt
grouse-0.4.2.dist-info/RECORD
