Metadata-Version: 2.1
Name: grouse
Version: 0.4.2
Summary: Evaluate Grounded Question Answering models and Grounded Question Answering evaluator models.
Author-email: Sacha Muller <sacha.muller@illuin.tech>, Antonio Loison <antonio.loison@illuin.tech>, Bilel Omrani <bilel.omrani@illuin.tech>
Project-URL: homepage, https://github.com/illuin-tech/grouse
Project-URL: repository, https://github.com/illuin-tech/grouse
Classifier: Programming Language :: Python :: 3
Classifier: Programming Language :: Python :: 3.10
Classifier: Programming Language :: Python :: 3.11
Classifier: Programming Language :: Python :: 3.12
Requires-Python: <3.13,>=3.10
License-File: LICENSE.txt
Requires-Dist: click <8.1.7,>=8.1.0
Requires-Dist: litellm <2.0.0,>=1.41.0
Requires-Dist: diskcache <6.0.0,>=5.6.0
Requires-Dist: numpy <3.0.0,>=1.21.2
Requires-Dist: jsonlines <5.0.0,>=4.0.0
Requires-Dist: datasets ==2.20.0
Requires-Dist: Jinja2 <4.0.0,>=3.1.0
Requires-Dist: tqdm <5.0.0,>=4.66.0
Requires-Dist: pydantic <3.0.0,>=2.5.0
Requires-Dist: matplotlib <4.0.0,>=3.9.0
Requires-Dist: importlib-resources <7.0.0,>=6.4.0
Provides-Extra: dev
Requires-Dist: ruff ==0.5.4 ; extra == 'dev'
Requires-Dist: deptry ==0.17.0 ; extra == 'dev'
Requires-Dist: mypy ==1.11.0 ; extra == 'dev'
Requires-Dist: pytest ==8.3.1 ; extra == 'dev'
Requires-Dist: coverage ==7.6.0 ; extra == 'dev'
Requires-Dist: types-tqdm ==4.66.0 ; extra == 'dev'
Requires-Dist: mock ==5.1.0 ; extra == 'dev'
